MANIFEST.in
setup.py
edgesense/__init__.py
edgesense/build_network.py
edgesense/catalyst_server.py
edgesense/drupal_script.py
edgesense/parse_catalyst.py
edgesense/parse_mailinglist.py
edgesense/parse_tweets.py
edgesense.egg-info/PKG-INFO
edgesense.egg-info/SOURCES.txt
edgesense.egg-info/dependency_links.txt
edgesense.egg-info/entry_points.txt
edgesense.egg-info/pbr.json
edgesense.egg-info/requires.txt
edgesense.egg-info/top_level.txt
edgesense/catalyst/__init__.py
edgesense/catalyst/inference.py
edgesense/catalyst/namespaces.py
edgesense/catalyst/extract/__init__.py
edgesense/catalyst/extract/excerpts.py
edgesense/catalyst/extract/ideas.py
edgesense/catalyst/extract/simple.py
edgesense/catalyst/ontology/assembl_core.ttl
edgesense/catalyst/ontology/catalyst_aif.ttl
edgesense/catalyst/ontology/catalyst_core.ttl
edgesense/catalyst/ontology/catalyst_ibis.ttl
edgesense/catalyst/ontology/catalyst_ibis_extra.ttl
edgesense/catalyst/ontology/catalyst_idea.ttl
edgesense/catalyst/ontology/catalyst_idea_extra.ttl
edgesense/catalyst/ontology/catalyst_vote.ttl
edgesense/catalyst/ontology/dcterms.ttl
edgesense/catalyst/ontology/foaf.ttl
edgesense/catalyst/ontology/openannotation.ttl
edgesense/catalyst/ontology/owl.ttl
edgesense/catalyst/ontology/rdf-schema.ttl
edgesense/catalyst/ontology/sioc.ttl
edgesense/catalyst/ontology/sioc_arg.ttl
edgesense/catalyst/ontology/swan-sioc.ttl
edgesense/catalyst/ontology/version.ttl
edgesense/content/__init__.py
edgesense/content/metrics.py
edgesense/mailinglist/__init__.py
edgesense/mailinglist/parse.py
edgesense/mailinglist/threading.py
edgesense/metrics/__init__.py
edgesense/network/__init__.py
edgesense/network/metrics.py
edgesense/network/utils.py
edgesense/twitter/__init__.py
edgesense/twitter/extract.py
edgesense/twitter/parse.py
edgesense/utils/__init__.py
edgesense/utils/datapackage_template.json
edgesense/utils/extract.py
edgesense/utils/gexf.py
edgesense/utils/logger_initializer.py
edgesense/utils/resource.py