Metadata-Version: 1.0
Name: edgesense
Version: 0.22.0
Summary: Edgesense Social Network Analysis and Visualization
Home-page: https://github.com/Wikitalia/edgesense/python
Author: Luca Mearelli
Author-email: l.mearelli@spazidigitali.com
License: MIT
Keywords: edgesense sna network socialnetwork catalyst
Platform: UNKNOWN
Classifier: Development Status :: 4 - Beta
Classifier: Intended Audience :: Developers
Classifier: Intended Audience :: Science/Research
Classifier: Topic :: Scientific/Engineering
Classifier: Topic :: Software Development :: Libraries
Classifier: License :: OSI Approved :: MIT License
Classifier: Programming Language :: Python :: 2
Classifier: Programming Language :: Python :: 2.6
Classifier: Programming Language :: Python :: 2.7
